scs_re
scs_sre
